arango_taxii_server/__init__.py
arango_taxii_server/asgi.py
arango_taxii_server/celery.py
arango_taxii_server/conf.py
arango_taxii_server/settings.py
arango_taxii_server/urls.py
arango_taxii_server/wsgi.py
arango_taxii_server/app/__init__.py
arango_taxii_server/app/admin.py
arango_taxii_server/app/apps.py
arango_taxii_server/app/arango_helper.py
arango_taxii_server/app/authentication.py
arango_taxii_server/app/models.py
arango_taxii_server/app/open_api_schemas.py
arango_taxii_server/app/schema_views.py
arango_taxii_server/app/serializers.py
arango_taxii_server/app/settings.py
arango_taxii_server/app/task_helpers.py
arango_taxii_server/app/tests.py
arango_taxii_server/app/urls.py
arango_taxii_server/app/utils.py
arango_taxii_server/app/views.py
arango_taxii_server/app/migrations/0001_initial.py
arango_taxii_server/app/migrations/0002_alter_uploadtask_password.py
arango_taxii_server/app/migrations/0003_remove_objectstatus_stix_data_json.py
arango_taxii_server/app/migrations/__init__.py
arango_taxii_server-1.1.5.dist-info/METADATA
arango_taxii_server-1.1.5.dist-info/WHEEL
arango_taxii_server-1.1.5.dist-info/licenses/LICENSE
arango_taxii_server-1.1.5.dist-info/RECORD
