Metadata-Version: 2.4
Name: arango_taxii_server
Version: 1.1.5
Summary: A lightweight TAXII API wrapper for ArangoDB.
Project-URL: Homepage, https://github.com/muchdogesec/arango_taxii_server
Project-URL: Issues, https://github.com/muchdogesec/arango_taxii_server/issues
Project-URL: dogesec HQ, https://dogesec.com
Author: dogesec
Maintainer: dogesec
License-File: LICENSE
Classifier: License :: OSI Approved :: Apache Software License
Classifier: Operating System :: OS Independent
Classifier: Programming Language :: Python :: 3
Requires-Python: >=3.9
Requires-Dist: celery>=5.4.0; python_version >= '3.8'
Requires-Dist: django-cors-headers
Requires-Dist: djangorestframework>=3.15.2
Requires-Dist: drf-spectacular>=0.27.2
Requires-Dist: python-arango>=8.1.3; python_version >= '3.8'
Requires-Dist: stix2arango>=1.0.3
Provides-Extra: full
Requires-Dist: psycopg2-binary>=2.9.10; (python_version >= '3.7') and extra == 'full'
Requires-Dist: redis>=5.1.0b5; (python_version >= '3.8') and extra == 'full'
